{"$schema":"https://json-schema.org/draft/2020-12/schema","type":"object","required":["assertion_id","source_item_id","source_system","subject_type","subject_label_as_printed","predicate","object_type","object_label_as_printed","confidence","assertion_status"],"properties":{"assertion_id":{"type":"string","pattern":"^assertion:"},"source_item_id":{"type":"string","pattern":"^source-item:"},"source_system":{"type":"string"},"assertion_status":{"type":"string"},"public_claim_status":{"type":"string"},"license":{"type":"string"},"attribution_required":{"type":"boolean"}},"additionalProperties":true}
